simpleneighbors/__init__.py
simpleneighbors/benchmark.py
simpleneighbors/backends/__init__.py
simpleneighbors/backends/annoy_.py
simpleneighbors/backends/base.py
simpleneighbors/backends/bruteforcepurepython.py
simpleneighbors/backends/sklearn_.py
simpleneighbors-0.1.0.dist-info/LICENSE.txt
simpleneighbors-0.1.0.dist-info/METADATA
simpleneighbors-0.1.0.dist-info/RECORD
simpleneighbors-0.1.0.dist-info/WHEEL
simpleneighbors-0.1.0.dist-info/top_level.txt
