Metadata-Version: 2.1
Name: simpleneighbors
Version: 0.1.0
Summary: A clean and easy interface for nearest-neighbors lookup
Home-page: https://github.com/aparrish/simpleneighbors
Author: Allison Parrish
Author-email: allison@decontextualize.com
License: UNKNOWN
Platform: any
Classifier: Development Status :: 3 - Alpha
Classifier: Intended Audience :: Developers
Classifier: Intended Audience :: Education
Classifier: Intended Audience :: Science/Research
Classifier: Programming Language :: Python
Classifier: License :: OSI Approved :: MIT License
Classifier: Topic :: Artistic Software
Classifier: Topic :: Software Development :: Libraries
Provides-Extra: purepython
Provides-Extra: dev
Provides-Extra: sklearn
Provides-Extra: annoy
Provides-Extra: annoy
Requires-Dist: annoy (>=1.16.0); extra == 'annoy'
Provides-Extra: dev
Requires-Dist: annoy (>=1.16.0); extra == 'dev'
Requires-Dist: scikit-learn (>=0.20); extra == 'dev'
Requires-Dist: coverage; extra == 'dev'
Requires-Dist: flake8; extra == 'dev'
Provides-Extra: dev
Requires-Dist: mock; (python_version <= "2.7") and extra == 'dev'
Provides-Extra: purepython
Provides-Extra: sklearn
Requires-Dist: scikit-learn (>=0.20); extra == 'sklearn'
